LICENSE.txt
MANIFEST.in
README.md
setup.py
rumboot/ImageFormatDb.py
rumboot/LayoutFactory.py
rumboot/OpFactory.py
rumboot/__init__.py
rumboot/chipDb.py
rumboot/classLoader.py
rumboot/cmdline.py
rumboot/edcl.py
rumboot/edclManager.py
rumboot/resetSeq.py
rumboot/scripting.py
rumboot/server.py
rumboot/terminal.py
rumboot/testing_old.py
rumboot/xfer.py
rumboot/chips/__init__.py
rumboot/chips/basis.yml
rumboot/chips/bbp3.yml
rumboot/chips/chipRPI4.yml
rumboot/chips/chipZynq.yml
rumboot/chips/chips_parameters.yml
rumboot/chips/mb7707.yml
rumboot/chips/mm7705.yml
rumboot/chips/nm6408.yml
rumboot/chips/o32t.yml
rumboot/chips/oi10.yml
rumboot/flashing/__init__.py
rumboot/flashing/base.py
rumboot/flashing/dumb.py
rumboot/flashing/flw_writer.py
rumboot/flashing/mb7707_edcl.py
rumboot/flashing/partitions.py
rumboot/flashing/util.py
rumboot/flashing/spl-tools/basis/u-boot-spl-dtb-i2c-mmc.rbi
rumboot/flashing/spl-tools/basis/u-boot-spl-dtb-i2c-sf.rbi
rumboot/flashing/spl-tools/bbp3/rumboot-bbp3-PostProduction-updater-spi0-cs0.bin
rumboot/flashing/spl-tools/mb7707/mboot-signed.bin
rumboot/flashing/spl-tools/mm7705/u-boot-spl-dtb-sf-nand-mmc.rbi
rumboot/flashing/spl-tools/mm7705/u-boot-spl-dtb-sf-nor-mmc.rbi
rumboot/flashing/spl-tools/o32t/rumboot-oi10-PostProduction-updater-nor-mt150.04-brom.bin
rumboot/flashing/spl-tools/o32t/rumboot-oi10-PostProduction-updater-nor-mt150.04.bin
rumboot/flashing/spl-tools/o32t/u-boot-spl-dtb-mmc.rbi
rumboot/flashing/spl-tools/o32t/u-boot-spl-dtb-sf.rbi
rumboot/flashing/spl-tools/oi10/rumboot-oi10-PostProduction-updater-nor-mt150.04-brom.bin
rumboot/flashing/spl-tools/oi10/rumboot-oi10-PostProduction-updater-nor-mt150.04.bin
rumboot/flashing/spl-tools/oi10/u-boot-spl-dtb-mmc.rbi
rumboot/flashing/spl-tools/oi10/u-boot-spl-dtb-sf.rbi
rumboot/images/__init__.py
rumboot/images/imageFormat1879.py
rumboot/images/imageFormatBase.py
rumboot/images/imageFormatLegacyNM6408.py
rumboot/images/imageFormatV1.py
rumboot/images/imageFormatV2.py
rumboot_tools.egg-info/PKG-INFO
rumboot_tools.egg-info/SOURCES.txt
rumboot_tools.egg-info/dependency_links.txt
rumboot_tools.egg-info/entry_points.txt
rumboot_tools.egg-info/requires.txt
rumboot_tools.egg-info/top_level.txt
