Metadata-Version: 2.1
Name: rumboot-tools
Version: 0.9.32
Summary: RumBoot ROM Loader Tools
Home-page: http://github.com/RC-MODULE/rumboot-tools
Author: Andrew Andrianov
Author-email: andrew@ncrmnt.org
License: GPL
Keywords: rumboot image
Platform: any
Classifier: Development Status :: 4 - Beta
Classifier: Environment :: Console
Classifier: Intended Audience :: Developers
Classifier: Operating System :: POSIX
Classifier: Operating System :: Microsoft :: Windows
Classifier: Operating System :: POSIX :: Linux
Classifier: Operating System :: MacOS
Classifier: Programming Language :: Python :: 3
Classifier: Programming Language :: Python :: 3.7
Classifier: Programming Language :: Python :: 3.8
Classifier: Programming Language :: Python :: 3.9
Classifier: Topic :: Software Development :: Embedded Systems
Classifier: Topic :: Software Development
License-File: LICENSE.txt
